emailonline/__init__.py
emailonline/apps.py
emailonline/models.py
emailonline/urls.py
emailonline/views.py
emailonline/migrations/0001_initial.py
emailonline/migrations/__init__.py
emailonline_beeflow-0.0.2.dist-info/LICENCE
emailonline_beeflow-0.0.2.dist-info/METADATA
emailonline_beeflow-0.0.2.dist-info/WHEEL
emailonline_beeflow-0.0.2.dist-info/top_level.txt
emailonline_beeflow-0.0.2.dist-info/RECORD
