Metadata-Version: 2.1
Name: emailonline-beeflow
Version: 0.0.2
Summary: Add 'see online' link to any email
Home-page: https://github.com/beeflow/emailonline.git
Author: Rafal Przetakowski
Author-email: office@beeflow.co.uk
License: UNKNOWN
Platform: UNKNOWN
Classifier: Programming Language :: Python :: 3
Classifier: License :: OSI Approved :: MIT License
Classifier: Operating System :: OS Independent
Requires-Python: >=3.8
